HedgeTech/__init__.py
hedgetech-0.0.0.dist-info/licenses/LICENSE
hedgetech-0.0.0.dist-info/licenses/NOTICE
hedgetech-0.0.0.dist-info/METADATA
hedgetech-0.0.0.dist-info/WHEEL
hedgetech-0.0.0.dist-info/top_level.txt
hedgetech-0.0.0.dist-info/RECORD
