Metadata-Version: 2.4
Name: HedgeTech
Version: 0.0.0
Summary: Core SDK for integrating with HedgeTech trading and market data APIs
Author-email: "hedgetech.ir" <info@hedgetech.ir>
License:                                  Apache License
Project-URL: Homepage, https://github.com/HedgeTech-ir/HedgeTech
Project-URL: Documentation, https://github.com/HedgeTech-ir/HedgeTech/blob/main/README.md
Project-URL: Repository, https://github.com/HedgeTech-ir/HedgeTech
Keywords: hedge,finance,trading,oms,api,market-data,execution,orderbook,algo-trading,async,sdk
Classifier: Programming Language :: Python :: 3
Classifier: License :: OSI Approved :: Apache Software License
Classifier: Operating System :: OS Independent
Classifier: Development Status :: 3 - Alpha
Classifier: Intended Audience :: Developers
Classifier: Intended Audience :: Financial and Insurance Industry
Classifier: Topic :: Software Development :: Libraries
Requires-Python: >=3.10
License-File: LICENSE
License-File: NOTICE
Requires-Dist: httpx[http2]==0.28.1
Dynamic: license-file
